[{"id":"052f0433-3b08-4bfe-9f67-f6296c1ce883","title":"New Year","type":"HOLIDAY","date":"2026-01-01","startTime":"09:00","endTime":"17:00"},{"id":"799b0007-f99c-4d97-9d25-2cd53813752a","title":"New Year's Eve","type":"OOO","date":"2025-12-31","startTime":"14:00","endTime":"17:00"},{"id":"052f0433-3b08-4bfe-9f67-f6296c1ce856","title":"Christmas","type":"HOLIDAY","date":"2025-12-25","startTime":"09:00","endTime":"17:00"},{"id":"06b9ff77-c421-4b5d-962b-2fe079848492","title":"Event 2","type":"REMINDER","date":"2025-12-30","startTime":"05:31","endTime":"10:54"},{"id":"d670bdc5-926e-4e01-b72e-419648e271b5","title":"Event 1","type":"REMINDER","date":"2025-12-30","startTime":"03:00","endTime":"04:15"},{"id":"4e09e267-05bf-4a27-89f2-fecb732df40a","title":"Event 3","type":"OOO","date":"2025-12-30","startTime":"10:55","endTime":"12:22"},{"id":"e56b520e-a456-4caa-be94-227de893ecc5","title":"Test Event to show today's events and remaining events","type":"REMINDER","date":"2025-12-31","startTime":"04:05","endTime":"04:25"}]